unitheme/__init__.py
unitheme-0.0.1.dist-info/METADATA
unitheme-0.0.1.dist-info/WHEEL
unitheme-0.0.1.dist-info/top_level.txt
unitheme-0.0.1.dist-info/RECORD
