Metadata-Version: 2.1
Name: unitheme
Version: 0.0.1
Summary: Theme manager
Home-page: https://github.com/michaeljhanley
Author: Michael
Author-email: michaelhanley11@gmail.com
Classifier: Programming Language :: Python :: 3
Classifier: License :: OSI Approved :: MIT License
Classifier: Operating System :: OS Independent
Requires-Python: >=3.6
